config/.env
config/settings.py
talkative_client/README.md
talkative_client/__init__.py
talkative_client/__main__.py
talkative_client/commands.py
talkative_client/contacts/commands.py
talkative_client/core.py
talkative_client/db.py
talkative_client/docs/Makefile
talkative_client/docs/_build/doctrees/client.doctree
talkative_client/docs/_build/doctrees/client.jim_mes.doctree
talkative_client/docs/_build/doctrees/environment.pickle
talkative_client/docs/_build/doctrees/index.doctree
talkative_client/docs/_build/html/.buildinfo
talkative_client/docs/_build/html/_modules/commands.html
talkative_client/docs/_build/html/_modules/core.html
talkative_client/docs/_build/html/_modules/db.html
talkative_client/docs/_build/html/_modules/dis.html
talkative_client/docs/_build/html/_modules/errors.html
talkative_client/docs/_build/html/_modules/gui.html
talkative_client/docs/_build/html/_modules/index.html
talkative_client/docs/_build/html/_modules/jim_mes/convert.html
talkative_client/docs/_build/html/_modules/jim_mes/jim.html
talkative_client/docs/_build/html/_modules/metaclasses.html
talkative_client/docs/_build/html/_modules/pathlib.html
talkative_client/docs/_build/html/_modules/sqlalchemy/orm/attributes.html
talkative_client/docs/_build/html/_sources/client.jim_mes.rst.txt
talkative_client/docs/_build/html/_sources/client.rst.txt
talkative_client/docs/_build/html/_sources/index.rst.txt
talkative_client/docs/_build/html/_static/_stemmer.js
talkative_client/docs/_build/html/_static/basic.css
talkative_client/docs/_build/html/_static/css/badge_only.css
talkative_client/docs/_build/html/_static/css/theme.css
talkative_client/docs/_build/html/_static/doctools.js
talkative_client/docs/_build/html/_static/documentation_options.js
talkative_client/docs/_build/html/_static/file.png
talkative_client/docs/_build/html/_static/fonts/Inconsolata-Bold.ttf
talkative_client/docs/_build/html/_static/fonts/Inconsolata-Regular.ttf
talkative_client/docs/_build/html/_static/fonts/Inconsolata.ttf
talkative_client-0.1.2.dist-info/WHEEL
talkative_client-0.1.2.dist-info/METADATA
talkative_client-0.1.2.dist-info/RECORD
